Workbook

Sheet Активное
A1: № | B1: Наименование | C1: Модель / Характеристики | D1: Кол-во | E1: Цена | F1: Сумма
A2: 1 | B2: Точка доступа | C2: Eltex WEP-200L 802.11 ac | D2: 4 | E2: 71205 | F2: =D2*E2 -> 284820
A3: 2 | B3: Ethernet-коммутатор | C3: Eltex MES2408 | D3: 1 | E3: 66791 | F3: =D3*E3 -> 66791
A4: 3 | B4: Сервер (ПК в сборке) | C4: Intel Core i5 / 16 ГБ ОЗУ / 2×1 ТБ HDD (RAID 1) | D4: 1 | E4: 52000 | F4: =D4*E4 -> 52000
A5: 4 | B5: ИБП для сервера | C5: 1000 ВА | D5: 1 | E5: 7490 | F5: =D5*E5 -> 7490
A6: 5 | B6: ИБП для коммутатора | C6: 500 ВА | D6: 1 | E6: 5990 | F6: =D6*E6 -> 5990
A17: Итого: | B17: =SUM(F2:F6) -> 417091

Sheet Пассивное
A1: № | B1: Наименование | C1: Характеристики | D1: Кол-во | E1: Цена за ед., руб. | F1: Сумма, руб. | G1: Ссылка на источник
A2: 1 | B2: Кабель UTP cat.5e (бухта 305 м) | C2: Медный, 24 AWG | D2: 1 | E2: 4850 | F2: =D2*E2 -> 4850
A3: 2 | B3: Кабельный канал 40×20 мм (2 м) | C3: Пластиковый | D3: 25 | E3: 180 | F3: =D3*E3 -> 4500
A4: 3 | B4: Розетка RJ-45 (одноместная) | C4: Категория 5e | D4: 10 | E4: 150 | F4: =D4*E4 -> 1500
A5: 4 | B5: Розетка RJ-45 (двухместная) | C5: Категория 5e | D5: 5 | E5: 250 | F5: =D5*E5 -> 1250
A6: 5 | B6: Патч-панель 12 портов | C6: Категория 5e, 19" | D6: 2 | E6: 2100 | F6: =D6*E6 -> 4200
A7: 6 | B7: Коннекторы RJ-45 (100 шт.) | C7: Категория 5e | D7: 1 | E7: 500 | F7: =D7*E7 -> 500
A8: 7 | B8: Маркеры кабельные (50 шт.) | C8: Самоклеящиеся | D8: 1 | E8: 300 | F8: =D8*E8 -> 300
A9: 8 | B9: Стяжки нейлоновые (100 шт.) | C9: 100×2,5 мм | D9: 1 | E9: 200 | F9: =D9*E9 -> 200
A10: 9 | B10: Кронштейн для точки доступа | C10: Для настенного/потолочного монтажа | D10: 4 | E10: 500 | F10: =D10*E10 -> 2000
A17: Итого: | B17: =SUM(F2:F10) -> 19300

Sheet ПО(-)
A1: № | B1: Наименование | C1: Кол-во лицензий | D1: Цена за ед., руб. | E1: Сумма, руб. | F1: Ссылка на источник
A2: 1 | B2: Astra Linux Special Edition | C2: 3 | D2: 21675 | E2: =C2*D2 -> 65025

Sheet Оплата труда
A1: Трудоёмкость и стоимость оплаты труда работников:
A2: Этап | B2: Должность | C2: Трудоёмкость, чел.-час | D2: Часовая ставка, руб.
A3: Разработка проекта и документации | B3: Системный архитектор | C3: 80 | D3: 357
A4: Монтаж и установка | B4: Инженер-монтажник | C4: 120 | D4: 268
A5: Пуско-наладочные работы | B5: Инженер-наладчик | C5: 100 | D5: 327

Sheet Смета работ
A1: Затраты на оплату труда работников
A2: Этап | B2: Трудоёмкость, чел.-час | C2: Час. ставка, руб. | D2: Сумма, руб.
A3: Разработка проекта | B3: ='Оплата труда'!C3 -> 80 | C3: ='Оплата труда'!D3 -> 357 | D3: =B3*C3 -> 28560
A4: Монтаж и установка | B4: ='Оплата труда'!C4 -> 120 | C4: ='Оплата труда'!D4 -> 268 | D4: =B4*C4 -> 32160
A5: Пуско-наладочные работы | B5: ='Оплата труда'!C5 -> 100 | C5: ='Оплата труда'!D5 -> 327 | D5: =B5*C5 -> 32700
A6: Итого | D6: =SUM(D3:D5) -> 93420
A8: Страховые взносы
A9: Оплата труда работников | B9: =D6 -> 93420
A10: Ставка страх. Взносов | B10: 0.302
A11: Итого | B11: =B9*B10 -> 28212.84

Sheet ИТОГО
A1: Оборудование
A2: Категория | B2: Сумма, руб.
A3: Активное оборудование | B3: =Активное!B17 -> 417091
A4: Пассивное оборудование | B4: =Пассивное!B17 -> 19300
A5: Итого: | B5: =SUM(B3:B4) -> 436391
A7: Сводная смета стоимости работ (единовременные затраты)
A8: Статья затрат | B8: Сумма, руб.
A9: Оборудование и материалы | B9: =B5 -> 436391
A10: Оплата труда работников | B10: ='Смета работ'!D6 -> 93420
A11: Страховые взносы | B11: ='Смета работ'!B11 -> 28212.84
A12: Итого: | B12: =SUM(B9:B11) -> 558023.84
A14: Годовые эксплуатационные затраты (после ввода сети в эксплуатацию)
A15: Статья затрат | B15: Расчёт
A16: Амортизация оборудования | B16: =B5/36*12 -> 145463.67
A17: Затраты на электроэнергию | B17: =0.213*24*365*7 -> 13061.16
A18: Оплата труда администратора (0,5 ставки) | B18: =25000*12 -> 300000
A19: Страховые взносы на администратора | B19: =300000*'Смета работ'!B10 -> 90600
A20: Итого: | B20: =SUM(B16:B19) -> 549124.83
